zoomeyehk/__init__.py
zoomeyehk/cli.py
zoomeyehk-2.2.2.dist-info/LICENSE
zoomeyehk-2.2.2.dist-info/METADATA
zoomeyehk-2.2.2.dist-info/WHEEL
zoomeyehk-2.2.2.dist-info/entry_points.txt
zoomeyehk-2.2.2.dist-info/top_level.txt
zoomeyehk-2.2.2.dist-info/RECORD
